winzy_webcam/__init__.py
winzy_webcam-0.1.3.dist-info/LICENSE
winzy_webcam-0.1.3.dist-info/METADATA
winzy_webcam-0.1.3.dist-info/WHEEL
winzy_webcam-0.1.3.dist-info/entry_points.txt
winzy_webcam-0.1.3.dist-info/top_level.txt
winzy_webcam-0.1.3.dist-info/RECORD
