Metadata-Version: 2.1
Name: winzy-webcam
Version: 0.1.3
Summary: Take image capture from webcam on laptop
Author: Sukhbinder Singh
License: Apache-2.0
Project-URL: Homepage, https://github.com/sukhbinder/winzy-webcam
Project-URL: Changelog, https://github.com/sukhbinder/winzy-webcam/releases
Project-URL: Issues, https://github.com/sukhbinder/winzy-webcam/issues
Project-URL: CI, https://github.com/sukhbinder/winzy-webcam/actions
Classifier: License :: OSI Approved :: Apache Software License
License-File: LICENSE
Requires-Dist: winzy
Requires-Dist: imageio
Requires-Dist: imageio-ffmpeg
Provides-Extra: test
Requires-Dist: pytest ; extra == 'test'
